setup.py
salure_helpers/sharepoint/__init__.py
salure_helpers/sharepoint/sharepoint.py
salure_helpers_sharepoint.egg-info/PKG-INFO
salure_helpers_sharepoint.egg-info/SOURCES.txt
salure_helpers_sharepoint.egg-info/dependency_links.txt
salure_helpers_sharepoint.egg-info/not-zip-safe
salure_helpers_sharepoint.egg-info/requires.txt
salure_helpers_sharepoint.egg-info/top_level.txt