Metadata-Version: 1.0
Name: salure-helpers-sharepoint
Version: 1.1.0
Summary: Sharepoint wrapper from Salure
Home-page: UNKNOWN
Author: D&A Salure
Author-email: support@salureconnnect.com
License: Salure License
Platform: UNKNOWN
